Metadata-Version: 2.1
Name: binance-sync
Version: 1.0.16
Summary: Binance REST API python implementation
Home-page: https://github.com/Ulisses1478/python-binance
Author: Sam McHardy, Ulisses
Author-email: ulisses@hevex.app
License: MIT
Keywords: binance exchange rest api bitcoin ethereum btc eth neo
Platform: UNKNOWN
Classifier: Intended Audience :: Developers
Classifier: License :: OSI Approved :: MIT License
Classifier: Operating System :: OS Independent
Classifier: Programming Language :: Python :: 3
Classifier: Programming Language :: Python :: 3.5
Classifier: Programming Language :: Python :: 3.6
Classifier: Programming Language :: Python :: 3.7
Classifier: Programming Language :: Python
Classifier: Topic :: Software Development :: Libraries :: Python Modules
License-File: LICENSE
